<annotation verified="no">
  <folder>training_data</folder>
  <filename>009004acb9ceeb19bd77f5abc2f623dd</filename>
  <path>/home/saikiran/HBRS/RD/training_data/009004acb9ceeb19bd77f5abc2f623dd.jpg</path>
  <source>
    <database>Unknown</database>
  </source>
  <size>
    <width>455</width>
    <height>256</height>
    <depth>3</depth>
  </size>
  <segmented>0</segmented>
  <object>
    <name>green</name>
    <pose>Unspecified</pose>
    <truncated>0</truncated>
    <difficult>0</difficult>
    <bndbox>
      <xmin>255</xmin>
      <ymin>100</ymin>
      <xmax>266</xmax>
      <ymax>116</ymax>
    </bndbox>
  </object>
  <object>
    <name>green</name>
    <pose>Unspecified</pose>
    <truncated>0</truncated>
    <difficult>0</difficult>
    <bndbox>
      <xmin>94</xmin>
      <ymin>106</ymin>
      <xmax>104</xmax>
      <ymax>122</ymax>
    </bndbox>
  </object>
</annotation>
