<annotation verified="no">
  <folder>training_set_batch1</folder>
  <filename>00a2d9ab98a419eceaa9f249ae72c2f9</filename>
  <path>/home/saikiran/HBRS/RD/training_set_batch1/00a2d9ab98a419eceaa9f249ae72c2f9.jpg</path>
  <source>
    <database>Unknown</database>
  </source>
  <size>
    <width>455</width>
    <height>256</height>
    <depth>3</depth>
  </size>
  <segmented>0</segmented>
  <object>
    <name>red</name>
    <pose>Unspecified</pose>
    <truncated>0</truncated>
    <difficult>0</difficult>
    <bndbox>
      <xmin>303</xmin>
      <ymin>106</ymin>
      <xmax>311</xmax>
      <ymax>119</ymax>
    </bndbox>
  </object>
  <object>
    <name>red</name>
    <pose>Unspecified</pose>
    <truncated>0</truncated>
    <difficult>0</difficult>
    <bndbox>
      <xmin>263</xmin>
      <ymin>106</ymin>
      <xmax>269</xmax>
      <ymax>118</ymax>
    </bndbox>
  </object>
  <object>
    <name>red</name>
    <pose>Unspecified</pose>
    <truncated>0</truncated>
    <difficult>0</difficult>
    <bndbox>
      <xmin>388</xmin>
      <ymin>134</ymin>
      <xmax>395</xmax>
      <ymax>145</ymax>
    </bndbox>
  </object>
  <object>
    <name>red</name>
    <pose>Unspecified</pose>
    <truncated>0</truncated>
    <difficult>0</difficult>
    <bndbox>
      <xmin>59</xmin>
      <ymin>132</ymin>
      <xmax>69</xmax>
      <ymax>149</ymax>
    </bndbox>
  </object>
</annotation>
