<annotation verified="no">
  <folder>training_set_batch2</folder>
  <filename>00a67a2cb74bbd0ec56e06dc4d8d36a1</filename>
  <path>/home/saikiran/HBRS/RD/training_set_batch2/00a67a2cb74bbd0ec56e06dc4d8d36a1.jpg</path>
  <source>
    <database>Unknown</database>
  </source>
  <size>
    <width>455</width>
    <height>256</height>
    <depth>3</depth>
  </size>
  <segmented>0</segmented>
  <object>
    <name>green</name>
    <pose>Unspecified</pose>
    <truncated>0</truncated>
    <difficult>0</difficult>
    <bndbox>
      <xmin>275</xmin>
      <ymin>27</ymin>
      <xmax>287</xmax>
      <ymax>52</ymax>
    </bndbox>
  </object>
  <object>
    <name>green</name>
    <pose>Unspecified</pose>
    <truncated>0</truncated>
    <difficult>0</difficult>
    <bndbox>
      <xmin>199</xmin>
      <ymin>23</ymin>
      <xmax>212</xmax>
      <ymax>48</ymax>
    </bndbox>
  </object>
</annotation>
