<annotation verified="no">
  <folder>training_set_batch3</folder>
  <filename>00a9068ef7d0276bc7e0ea509cde0e96</filename>
  <path>/home/saikiran/HBRS/RD/training_set_batch3/00a9068ef7d0276bc7e0ea509cde0e96.jpg</path>
  <source>
    <database>Unknown</database>
  </source>
  <size>
    <width>455</width>
    <height>256</height>
    <depth>3</depth>
  </size>
  <segmented>0</segmented>
  <object>
    <name>green</name>
    <pose>Unspecified</pose>
    <truncated>0</truncated>
    <difficult>0</difficult>
    <bndbox>
      <xmin>256</xmin>
      <ymin>48</ymin>
      <xmax>267</xmax>
      <ymax>74</ymax>
    </bndbox>
  </object>
  <object>
    <name>green</name>
    <pose>Unspecified</pose>
    <truncated>0</truncated>
    <difficult>0</difficult>
    <bndbox>
      <xmin>391</xmin>
      <ymin>70</ymin>
      <xmax>401</xmax>
      <ymax>95</ymax>
    </bndbox>
  </object>
</annotation>
