<annotation verified="no">
  <folder>training_data</folder>
  <filename>01aed6c9f34669a405e0eba9493ee84d</filename>
  <path>/home/saikiran/HBRS/RD/training_data/01aed6c9f34669a405e0eba9493ee84d.jpg</path>
  <source>
    <database>Unknown</database>
  </source>
  <size>
    <width>455</width>
    <height>256</height>
    <depth>3</depth>
  </size>
  <segmented>0</segmented>
  <object>
    <name>red</name>
    <pose>Unspecified</pose>
    <truncated>0</truncated>
    <difficult>0</difficult>
    <bndbox>
      <xmin>258</xmin>
      <ymin>67</ymin>
      <xmax>269</xmax>
      <ymax>96</ymax>
    </bndbox>
  </object>
  <object>
    <name>red</name>
    <pose>Unspecified</pose>
    <truncated>0</truncated>
    <difficult>0</difficult>
    <bndbox>
      <xmin>73</xmin>
      <ymin>59</ymin>
      <xmax>86</xmax>
      <ymax>79</ymax>
    </bndbox>
  </object>
</annotation>
