<annotation verified="no">
  <folder>training_data</folder>
  <filename>01f93463e546e98b666b40f1cbf05d0c</filename>
  <path>/home/saikiran/HBRS/RD/training_data/01f93463e546e98b666b40f1cbf05d0c.jpg</path>
  <source>
    <database>Unknown</database>
  </source>
  <size>
    <width>455</width>
    <height>256</height>
    <depth>3</depth>
  </size>
  <segmented>0</segmented>
  <object>
    <name>red</name>
    <pose>Unspecified</pose>
    <truncated>0</truncated>
    <difficult>0</difficult>
    <bndbox>
      <xmin>144</xmin>
      <ymin>31</ymin>
      <xmax>157</xmax>
      <ymax>40</ymax>
    </bndbox>
  </object>
  <object>
    <name>red</name>
    <pose>Unspecified</pose>
    <truncated>0</truncated>
    <difficult>0</difficult>
    <bndbox>
      <xmin>144</xmin>
      <ymin>90</ymin>
      <xmax>150</xmax>
      <ymax>101</ymax>
    </bndbox>
  </object>
</annotation>
