<annotation verified="no">
  <folder>training_set_batch1</folder>
  <filename>0a0a5927188affde058c30899963041e</filename>
  <path>/home/saikiran/HBRS/RD/training_set_batch1/0a0a5927188affde058c30899963041e.jpg</path>
  <source>
    <database>Unknown</database>
  </source>
  <size>
    <width>455</width>
    <height>256</height>
    <depth>3</depth>
  </size>
  <segmented>0</segmented>
  <object>
    <name>red</name>
    <pose>Unspecified</pose>
    <truncated>0</truncated>
    <difficult>0</difficult>
    <bndbox>
      <xmin>304</xmin>
      <ymin>64</ymin>
      <xmax>315</xmax>
      <ymax>91</ymax>
    </bndbox>
  </object>
  <object>
    <name>red</name>
    <pose>Unspecified</pose>
    <truncated>0</truncated>
    <difficult>0</difficult>
    <bndbox>
      <xmin>70</xmin>
      <ymin>112</ymin>
      <xmax>82</xmax>
      <ymax>134</ymax>
    </bndbox>
  </object>
</annotation>
