<annotation verified="no">
  <folder>training_set_batch2</folder>
  <filename>0a6f5d47e94de77f90dfd76be4699e03</filename>
  <path>/home/saikiran/HBRS/RD/training_set_batch2/0a6f5d47e94de77f90dfd76be4699e03.jpg</path>
  <source>
    <database>Unknown</database>
  </source>
  <size>
    <width>455</width>
    <height>256</height>
    <depth>3</depth>
  </size>
  <segmented>0</segmented>
  <object>
    <name>red</name>
    <pose>Unspecified</pose>
    <truncated>0</truncated>
    <difficult>0</difficult>
    <bndbox>
      <xmin>188</xmin>
      <ymin>85</ymin>
      <xmax>199</xmax>
      <ymax>103</ymax>
    </bndbox>
  </object>
  <object>
    <name>red</name>
    <pose>Unspecified</pose>
    <truncated>0</truncated>
    <difficult>0</difficult>
    <bndbox>
      <xmin>250</xmin>
      <ymin>123</ymin>
      <xmax>260</xmax>
      <ymax>136</ymax>
    </bndbox>
  </object>
</annotation>
