<annotation verified="no">
  <folder>training_set_batch3</folder>
  <filename>0a736ccb6e37e054b93de83993d347ec</filename>
  <path>/home/saikiran/HBRS/RD/training_set_batch3/0a736ccb6e37e054b93de83993d347ec.jpg</path>
  <source>
    <database>Unknown</database>
  </source>
  <size>
    <width>455</width>
    <height>256</height>
    <depth>3</depth>
  </size>
  <segmented>0</segmented>
  <object>
    <name>red</name>
    <pose>Unspecified</pose>
    <truncated>0</truncated>
    <difficult>0</difficult>
    <bndbox>
      <xmin>267</xmin>
      <ymin>16</ymin>
      <xmax>283</xmax>
      <ymax>44</ymax>
    </bndbox>
  </object>
  <object>
    <name>red</name>
    <pose>Unspecified</pose>
    <truncated>0</truncated>
    <difficult>0</difficult>
    <bndbox>
      <xmin>126</xmin>
      <ymin>13</ymin>
      <xmax>140</xmax>
      <ymax>41</ymax>
    </bndbox>
  </object>
  <object>
    <name>red</name>
    <pose>Unspecified</pose>
    <truncated>0</truncated>
    <difficult>0</difficult>
    <bndbox>
      <xmin>203</xmin>
      <ymin>90</ymin>
      <xmax>210</xmax>
      <ymax>105</ymax>
    </bndbox>
  </object>
  <object>
    <name>red</name>
    <pose>Unspecified</pose>
    <truncated>0</truncated>
    <difficult>0</difficult>
    <bndbox>
      <xmin>175</xmin>
      <ymin>119</ymin>
      <xmax>183</xmax>
      <ymax>130</ymax>
    </bndbox>
  </object>
</annotation>
