<annotation verified="no">
  <folder>training_set_batch2</folder>
  <filename>0a8a8f8b454b41cebe3d80e8e5790528</filename>
  <path>/home/saikiran/HBRS/RD/training_set_batch2/0a8a8f8b454b41cebe3d80e8e5790528.jpg</path>
  <source>
    <database>Unknown</database>
  </source>
  <size>
    <width>455</width>
    <height>256</height>
    <depth>3</depth>
  </size>
  <segmented>0</segmented>
  <object>
    <name>green</name>
    <pose>Unspecified</pose>
    <truncated>0</truncated>
    <difficult>0</difficult>
    <bndbox>
      <xmin>197</xmin>
      <ymin>30</ymin>
      <xmax>211</xmax>
      <ymax>57</ymax>
    </bndbox>
  </object>
  <object>
    <name>green</name>
    <pose>Unspecified</pose>
    <truncated>0</truncated>
    <difficult>0</difficult>
    <bndbox>
      <xmin>332</xmin>
      <ymin>107</ymin>
      <xmax>342</xmax>
      <ymax>126</ymax>
    </bndbox>
  </object>
</annotation>
