<annotation verified="no">
  <folder>training_set_batch5</folder>
  <filename>0b29a363c32e8dcad6548a81fdf10b42</filename>
  <path>/home/saikiran/HBRS/RD/training_set_batch5/0b29a363c32e8dcad6548a81fdf10b42.jpg</path>
  <source>
    <database>Unknown</database>
  </source>
  <size>
    <width>455</width>
    <height>256</height>
    <depth>3</depth>
  </size>
  <segmented>0</segmented>
  <object>
    <name>green</name>
    <pose>Unspecified</pose>
    <truncated>0</truncated>
    <difficult>0</difficult>
    <bndbox>
      <xmin>88</xmin>
      <ymin>97</ymin>
      <xmax>96</xmax>
      <ymax>111</ymax>
    </bndbox>
  </object>
  <object>
    <name>green</name>
    <pose>Unspecified</pose>
    <truncated>0</truncated>
    <difficult>0</difficult>
    <bndbox>
      <xmin>126</xmin>
      <ymin>102</ymin>
      <xmax>134</xmax>
      <ymax>117</ymax>
    </bndbox>
  </object>
  <object>
    <name>green</name>
    <pose>Unspecified</pose>
    <truncated>0</truncated>
    <difficult>0</difficult>
    <bndbox>
      <xmin>154</xmin>
      <ymin>111</ymin>
      <xmax>164</xmax>
      <ymax>124</ymax>
    </bndbox>
  </object>
  <object>
    <name>green</name>
    <pose>Unspecified</pose>
    <truncated>0</truncated>
    <difficult>0</difficult>
    <bndbox>
      <xmin>201</xmin>
      <ymin>133</ymin>
      <xmax>209</xmax>
      <ymax>144</ymax>
    </bndbox>
  </object>
  <object>
    <name>green</name>
    <pose>Unspecified</pose>
    <truncated>0</truncated>
    <difficult>0</difficult>
    <bndbox>
      <xmin>323</xmin>
      <ymin>107</ymin>
      <xmax>335</xmax>
      <ymax>130</ymax>
    </bndbox>
  </object>
</annotation>
