<annotation verified="no">
  <folder>training_set_batch5</folder>
  <filename>0c2a4d8cdb6fcf2b04fecbf5aa9caba5</filename>
  <path>/home/saikiran/HBRS/RD/training_set_batch5/0c2a4d8cdb6fcf2b04fecbf5aa9caba5.jpg</path>
  <source>
    <database>Unknown</database>
  </source>
  <size>
    <width>455</width>
    <height>256</height>
    <depth>3</depth>
  </size>
  <segmented>0</segmented>
  <object>
    <name>red</name>
    <pose>Unspecified</pose>
    <truncated>0</truncated>
    <difficult>0</difficult>
    <bndbox>
      <xmin>287</xmin>
      <ymin>59</ymin>
      <xmax>300</xmax>
      <ymax>88</ymax>
    </bndbox>
  </object>
  <object>
    <name>red</name>
    <pose>Unspecified</pose>
    <truncated>0</truncated>
    <difficult>0</difficult>
    <bndbox>
      <xmin>397</xmin>
      <ymin>60</ymin>
      <xmax>412</xmax>
      <ymax>89</ymax>
    </bndbox>
  </object>
</annotation>
