<annotation verified="no">
  <folder>training_set_batch5</folder>
  <filename>0c5b0c8b9e4d1f2c0c5c6b03b7a74e89</filename>
  <path>/home/saikiran/HBRS/RD/training_set_batch5/0c5b0c8b9e4d1f2c0c5c6b03b7a74e89.jpg</path>
  <source>
    <database>Unknown</database>
  </source>
  <size>
    <width>455</width>
    <height>256</height>
    <depth>3</depth>
  </size>
  <segmented>0</segmented>
  <object>
    <name>red</name>
    <pose>Unspecified</pose>
    <truncated>0</truncated>
    <difficult>0</difficult>
    <bndbox>
      <xmin>408</xmin>
      <ymin>68</ymin>
      <xmax>420</xmax>
      <ymax>88</ymax>
    </bndbox>
  </object>
  <object>
    <name>red</name>
    <pose>Unspecified</pose>
    <truncated>0</truncated>
    <difficult>0</difficult>
    <bndbox>
      <xmin>350</xmin>
      <ymin>71</ymin>
      <xmax>362</xmax>
      <ymax>91</ymax>
    </bndbox>
  </object>
  <object>
    <name>red</name>
    <pose>Unspecified</pose>
    <truncated>0</truncated>
    <difficult>0</difficult>
    <bndbox>
      <xmin>226</xmin>
      <ymin>115</ymin>
      <xmax>239</xmax>
      <ymax>135</ymax>
    </bndbox>
  </object>
</annotation>
