<annotation verified="no">
  <folder>training_set_batch5</folder>
  <filename>0cf0d017b28a1c76da482ce4df4a60e1</filename>
  <path>/home/saikiran/HBRS/RD/training_set_batch5/0cf0d017b28a1c76da482ce4df4a60e1.jpg</path>
  <source>
    <database>Unknown</database>
  </source>
  <size>
    <width>455</width>
    <height>256</height>
    <depth>3</depth>
  </size>
  <segmented>0</segmented>
  <object>
    <name>red</name>
    <pose>Unspecified</pose>
    <truncated>0</truncated>
    <difficult>0</difficult>
    <bndbox>
      <xmin>380</xmin>
      <ymin>11</ymin>
      <xmax>399</xmax>
      <ymax>49</ymax>
    </bndbox>
  </object>
  <object>
    <name>red</name>
    <pose>Unspecified</pose>
    <truncated>0</truncated>
    <difficult>0</difficult>
    <bndbox>
      <xmin>314</xmin>
      <ymin>93</ymin>
      <xmax>324</xmax>
      <ymax>113</ymax>
    </bndbox>
  </object>
</annotation>
