<annotation verified="no">
  <folder>training_data</folder>
  <filename>f7eb21777cf9dca536c9db3d0c915c26</filename>
  <path>/home/saikiran/HBRS/RD/training_data/f7eb21777cf9dca536c9db3d0c915c26.jpg</path>
  <source>
    <database>Unknown</database>
  </source>
  <size>
    <width>455</width>
    <height>256</height>
    <depth>3</depth>
  </size>
  <segmented>0</segmented>
  <object>
    <name>red</name>
    <pose>Unspecified</pose>
    <truncated>0</truncated>
    <difficult>0</difficult>
    <bndbox>
      <xmin>357</xmin>
      <ymin>122</ymin>
      <xmax>364</xmax>
      <ymax>139</ymax>
    </bndbox>
  </object>
  <object>
    <name>red</name>
    <pose>Unspecified</pose>
    <truncated>0</truncated>
    <difficult>0</difficult>
    <bndbox>
      <xmin>144</xmin>
      <ymin>116</ymin>
      <xmax>153</xmax>
      <ymax>129</ymax>
    </bndbox>
  </object>
</annotation>
