<annotation verified="no">
  <folder>training_data</folder>
  <filename>fce44e678af9b40e26db70d9c0f4d309</filename>
  <path>/home/saikiran/HBRS/RD/training_data/fce44e678af9b40e26db70d9c0f4d309.jpg</path>
  <source>
    <database>Unknown</database>
  </source>
  <size>
    <width>455</width>
    <height>256</height>
    <depth>3</depth>
  </size>
  <segmented>0</segmented>
  <object>
    <name>red</name>
    <pose>Unspecified</pose>
    <truncated>0</truncated>
    <difficult>0</difficult>
    <bndbox>
      <xmin>357</xmin>
      <ymin>39</ymin>
      <xmax>369</xmax>
      <ymax>63</ymax>
    </bndbox>
  </object>
  <object>
    <name>red</name>
    <pose>Unspecified</pose>
    <truncated>0</truncated>
    <difficult>0</difficult>
    <bndbox>
      <xmin>145</xmin>
      <ymin>75</ymin>
      <xmax>153</xmax>
      <ymax>94</ymax>
    </bndbox>
  </object>
</annotation>
